dkdrlahel/__init__.py
dkdrlahel/__main__.py
dkdrlahel/adb_handler.py
dkdrlahel/config_manager.py
dkdrlahel/csv_handler.py
dkdrlahel/feature_handler.py
dkdrlahel/game_data_getter.py
dkdrlahel/helper.py
dkdrlahel/item.py
dkdrlahel/locale_handler.py
dkdrlahel/managed_item.py
dkdrlahel/parse_save.py
dkdrlahel/patcher.py
dkdrlahel/root_handler.py
dkdrlahel/serialise_save.py
dkdrlahel/server_handler.py
dkdrlahel/tracker.py
dkdrlahel/updater.py
dkdrlahel/user_input_handler.py
dkdrlahel/edits/__init__.py
dkdrlahel/edits/basic/__init__.py
dkdrlahel/edits/basic/basic_items.py
dkdrlahel/edits/basic/catfruit.py
dkdrlahel/edits/basic/catseyes.py
dkdrlahel/edits/basic/ototo_base_mats.py
dkdrlahel/edits/basic/talent_orbs.py
dkdrlahel/edits/basic/talent_orbs_new.py
dkdrlahel/edits/cats/__init__.py
dkdrlahel/edits/cats/cat_helper.py
dkdrlahel/edits/cats/cat_id_selector.py
dkdrlahel/edits/cats/chara_drop.py
dkdrlahel/edits/cats/clear_cat_guide.py
dkdrlahel/edits/cats/evolve_cats.py
dkdrlahel/edits/cats/get_remove_cats.py
dkdrlahel/edits/cats/talents.py
dkdrlahel/edits/cats/upgrade_blue.py
dkdrlahel/edits/cats/upgrade_cats.py
dkdrlahel/edits/gamototo/__init__.py
dkdrlahel/edits/gamototo/fix_gamatoto.py
dkdrlahel/edits/gamototo/gamatoto_xp.py
dkdrlahel/edits/gamototo/helpers.py
dkdrlahel/edits/gamototo/ototo_cat_cannon.py
dkdrlahel/edits/levels/__init__.py
dkdrlahel/edits/levels/aku.py
dkdrlahel/edits/levels/allow_filibuster_clearing.py
dkdrlahel/edits/levels/behemoth_culling.py
dkdrlahel/edits/levels/clear_tutorial.py
dkdrlahel/edits/levels/enigma_stages.py
dkdrlahel/edits/levels/event_stages.py
dkdrlahel/edits/levels/gauntlet.py
dkdrlahel/edits/levels/itf_timed_scores.py
dkdrlahel/edits/levels/legend_quest.py
dkdrlahel/edits/levels/main_story.py
dkdrlahel/edits/levels/outbreaks.py
dkdrlahel/edits/levels/story_level_id_selector.py
dkdrlahel/edits/levels/towers.py
dkdrlahel/edits/levels/treasures.py
dkdrlahel/edits/levels/uncanny.py
dkdrlahel/edits/levels/unlock_aku_realm.py
dkdrlahel-0.0.3.dist-info/METADATA
dkdrlahel-0.0.3.dist-info/WHEEL
dkdrlahel-0.0.3.dist-info/top_level.txt
dkdrlahel-0.0.3.dist-info/RECORD
